hier_client/__init__.py
hier_client/__version__.py
hier_client/client.py
hier_client/forward_emails.py
hier_client/test.py
hier_client/tree2pdf.py
hier_client-0.1.5.dist-info/LICENSE
hier_client-0.1.5.dist-info/METADATA
hier_client-0.1.5.dist-info/WHEEL
hier_client-0.1.5.dist-info/entry_points.txt
hier_client-0.1.5.dist-info/top_level.txt
hier_client-0.1.5.dist-info/RECORD
