Metadata-Version: 2.1
Name: hier-client
Version: 0.1.5
Summary: Python library for using Hier from the CLI.
Home-page: https://github.com/Jessime/hier_client
Author: Jessime Kirk
Author-email: jessime.kirk@gmail.com
License: MIT
Platform: UNKNOWN
Classifier: License :: OSI Approved :: MIT License
Classifier: Natural Language :: English
Classifier: Programming Language :: Python :: 3.6
Classifier: Programming Language :: Python :: 3.7
Requires-Dist: anvil-uplink
Requires-Dist: keyring
